{"version":1,"savedAt":1783289469789,"entries":{"48oT2QgpyPFUiJYXbvZTS1tVDp98R9uYAJX5ojNrpump":{"symbol":"SEMAN","name":"The Seed of Potential","grade":"GOLD","mode":"SWING","entryPrice":0.000120283,"entryAt":1783272050381,"nextTargetIdx":0,"msgId":19195,"threadId":171,"bought":false,"autoBuyStatus":"OFF","autoBuyReason":"AUTO_BUY_ENABLED=false","autoBuyCheckedAt":1783272050382},"FMqh9mqR6drPZqqW6wPqLHxX4rqNDWGhYLaMfoaJpump":{"symbol":"world","name":"world.xyz","grade":"GOLD","mode":"SWING","entryPrice":0.00337844,"entryAt":1783273926650,"nextTargetIdx":0,"msgId":19200,"threadId":171,"bought":false,"autoBuyStatus":"OFF","autoBuyReason":"AUTO_BUY_ENABLED=false","autoBuyCheckedAt":1783273926650},"6rC1CqY86w72nDZAMxrXbhZVbWgREAoiogPk1xFzpump":{"symbol":"CEEZEE","name":"Cee Zee","grade":"POTENSIAL","mode":"MIGRATION","entryPrice":0.0000379813035987,"entryAt":1783279130946,"nextTargetIdx":4,"msgId":19211,"threadId":12523,"bought":false,"autoBuyStatus":"OFF","autoBuyReason":"AUTO_BUY_ENABLED=false","autoBuyCheckedAt":1783279130946},"HEU5mPDm5jCyn4AjQKjvWuvttACKvitgpAdwfmu2DoiA":{"symbol":"CLIVE","name":"The Bagworker","grade":"GOLD","mode":"SWING","entryPrice":0.000284216,"entryAt":1783280487910,"nextTargetIdx":0,"msgId":19221,"threadId":171,"bought":false,"autoBuyStatus":"OFF","autoBuyReason":"AUTO_BUY_ENABLED=false","autoBuyCheckedAt":1783280487910},"BcHEaaTCvycPwwsJ9yQTXdHP9X2gCLkznDbZ8VySpump":{"symbol":"Jotchua","name":"Jotchua","grade":"GOLD","mode":"SWING","entryPrice":0.00689622,"entryAt":1783281511472,"nextTargetIdx":0,"msgId":19223,"threadId":171,"bought":false,"autoBuyStatus":"OFF","autoBuyReason":"AUTO_BUY_ENABLED=false","autoBuyCheckedAt":1783281511472},"7f5vGM47S6oSSDHnyPLwem2Nn4fy8WNXYvMwDWCBLiEt":{"symbol":"CEEZEE","name":"Cee Zee","grade":"POTENSIAL","mode":"MIGRATION","entryPrice":0.000054357412295965,"entryAt":1783281586719,"nextTargetIdx":3,"msgId":19225,"threadId":12523,"bought":false,"autoBuyStatus":"OFF","autoBuyReason":"AUTO_BUY_ENABLED=false","autoBuyCheckedAt":1783281586719},"cvkarf1CtN3tbLRk961vsaEf4T8QbnihDkCHa93pump":{"symbol":"NEIL","name":"Neil the Seal","grade":"GOLD","mode":"SWING","entryPrice":0.000426045,"entryAt":1783283972564,"nextTargetIdx":0,"msgId":19235,"threadId":171,"bought":false,"autoBuyStatus":"OFF","autoBuyReason":"AUTO_BUY_ENABLED=false","autoBuyCheckedAt":1783283972565}}}